deepcubeai/__init__.py
deepcubeai/main.py
deepcubeai/data/cube3/search_test/search_test_data.pkl
deepcubeai/data/cube3/search_test/search_test_data_reverse.pkl
deepcubeai/data/sokoban/search_test/search_test_data.pkl
deepcubeai/environments/__init__.py
deepcubeai/environments/cube3.py
deepcubeai/environments/digit_jump.py
deepcubeai/environments/environment_abstract.py
deepcubeai/environments/ice_slider.py
deepcubeai/environments/sokoban.py
deepcubeai/environments/puzzlegen/__init__.py
deepcubeai/environments/puzzlegen/base.py
deepcubeai/environments/puzzlegen/dice_puzzle.py
deepcubeai/environments/puzzlegen/ice_puzzle.py
deepcubeai/environments/puzzlegen/data/faces.csv
deepcubeai/environments/puzzlegen/data/goal.png
deepcubeai/environments/puzzlegen/data/ice.png
deepcubeai/environments/puzzlegen/data/mnist.csv
deepcubeai/environments/puzzlegen/data/player.png
deepcubeai/environments/puzzlegen/data/rock.png
deepcubeai/environments/sokoban_data/goal_states.zip
deepcubeai/environments/sokoban_data/surface/box.png
deepcubeai/environments/sokoban_data/surface/floor.png
deepcubeai/environments/sokoban_data/surface/player.png
deepcubeai/environments/sokoban_data/surface/wall.png
deepcubeai/extra/__init__.py
deepcubeai/extra/offline_data_viz.py
deepcubeai/extra/plot_disc_vs_cont.py
deepcubeai/extra/plot_perf.py
deepcubeai/scripts/__init__.py
deepcubeai/scripts/compare_solutions.py
deepcubeai/scripts/encode_offline_data.py
deepcubeai/scripts/generate_offline_data.py
deepcubeai/scripts/generate_search_test_data.py
deepcubeai/scripts/pipeline.sh
deepcubeai/scripts/pipeline_arg_handler.sh
deepcubeai/scripts/test_model_cont.py
deepcubeai/scripts/test_model_disc.py
deepcubeai/search_methods/__init__.py
deepcubeai/search_methods/gbfs_imag.py
deepcubeai/search_methods/qstar_imag.py
deepcubeai/search_methods/ucs_imag.py
deepcubeai/training/__init__.py
deepcubeai/training/qlearning.py
deepcubeai/training/qlearning_dist.py
deepcubeai/training/train_env_cont.py
deepcubeai_2-0.1.12.dist-info/LICENSE
deepcubeai_2-0.1.12.dist-info/METADATA
deepcubeai_2-0.1.12.dist-info/WHEEL
deepcubeai_2-0.1.12.dist-info/entry_points.txt
deepcubeai_2-0.1.12.dist-info/top_level.txt
deepcubeai_2-0.1.12.dist-info/RECORD
