Metadata-Version: 2.1
Name: deepcubeai_2
Version: 0.1.12
Summary: Learning Discrete World Models for Heuristic Search
Author-email: Misagh Soltani <msoltani@email.sc.edu>
License: MIT License
Project-URL: Repository, https://github.com/misaghsoltani/DeepCubeAI_2/
Project-URL: Paper, https://rlj.cs.umass.edu/2024/papers/Paper225.html
Keywords: DeepCubeAI,DeepCubeA,DeepCube,DeepXube,deep learning,reinforcement learning,deep reinforcement learning,search,heuristic search,pathfinding,planning,Rubik's Cube,Sokoban,Q*,model-based reinforcement learning,discrete world model,deep q-learning,deep q-network,Q* search
Classifier: Programming Language :: Python :: 3
Classifier: License :: OSI Approved :: MIT License
Classifier: Operating System :: OS Independent
Requires-Python: >=3.10
License-File: LICENSE
Requires-Dist: torch >=2.0
Requires-Dist: numpy ==1.*
Requires-Dist: matplotlib
Requires-Dist: scikit-learn
Requires-Dist: networkx
Requires-Dist: imageio
Requires-Dist: imageio-ffmpeg
Requires-Dist: gym
Requires-Dist: opencv-python-headless
Requires-Dist: openmpi
Requires-Dist: mpi
